tests/__init__.py
tts_capture/__init__.py
tts_capture/cli.py
tts_capture-0.1.1.dist-info/LICENSE
tts_capture-0.1.1.dist-info/METADATA
tts_capture-0.1.1.dist-info/WHEEL
tts_capture-0.1.1.dist-info/top_level.txt
tts_capture-0.1.1.dist-info/RECORD
