Metadata-Version: 2.1
Name: tts-capture
Version: 0.1.1
Summary: A project that uses OpenAI Whisper for transcription and PyAudio for mic input.
Home-page: https://github.com/obahamonde/tts-capture
Author: Oscar Bahamonde
Author-email: oscar.bahamonde.dev@gmail.com
Classifier: Programming Language :: Python :: 3
Classifier: License :: OSI Approved :: MIT License
Classifier: Operating System :: OS Independent
Requires-Python: >=3.6
License-File: LICENSE
Requires-Dist: openai
Requires-Dist: openai-whisper
Requires-Dist: pyaudio
